<?xml version="1.0" encoding="UTF-8" ?>
<!DOCTYPE mapper
  PUBLIC "-//mybatis.org//DTD Mapper 3.0//EN" "http://mybatis.org/dtd/mybatis-3-mapper.dtd">
<mapper namespace="com.spacerental.mapper.SpaceMapper">
	<sql id="spaceBasicColumns">
		spaceNo, spaceName, type, content, maximum, bim, smoking, food, wifi, computer, hostid
	</sql>
	<sql id="spaceFileBasicColumns">
		spaceFileNo, spaceNo, savedFileName, flag
	</sql>
	<select id="selectSpace">
		SELECT <include refid="spaceBasicColumns" /> FROM SPACE 
	</select>
	
	<select id="selectSpaceFile">
		SELECT <include refid="spaceFileBasicColumns" /> FROM SPACEFILE
	</select>
	
	<insert id="insertSpace" parameterType="Space">
		<selectKey keyProperty="spaceNo" order="AFTER" resultType="int">
			SELECT SPACE_SEQUENCE.CURRVAL FROM DUAL
		</selectKey>
		INSERT INTO SPACE(
			spaceNo, spaceName, content, maximum, bim, smoking, food, wifi, computer, hostNo, hostId
		)
		VALUES
		(
			SPACE_SEQUENCE.NEXTVAL
			, #{ spaceName }
			, #{ content }
			, #{ maximum }
			, #{ bim }
			, #{ smoking }
			, #{ food }
			, #{ wifi }
			, #{ computer }
			, #{ hostNo }
			, #{ hostId }
		)
	</insert>
	
	<insert id="insertSpaceFile" parameterType="SpaceFile">
		INSERT INTO SpaceFILE(
			<include refid="spaceFileBasicColumns" />
		)
		VALUES
		(
			SPACEFILE_SEQUENCE.NEXTVAL
			, #{ spaceNo }
			, #{ savedFileName }
			, #{ flag }
		)
	</insert>
</mapper>